azureblobfs/__init__.py
azureblobfs/utils.py
azureblobfs/dask/__init__.py
azureblobfs/dask/mapping.py
azureblobfs/fs/__init__.py
dask_azureblobfs-0.1.0.dist-info/METADATA
dask_azureblobfs-0.1.0.dist-info/RECORD
dask_azureblobfs-0.1.0.dist-info/WHEEL
dask_azureblobfs-0.1.0.dist-info/top_level.txt
