Metadata-Version: 2.1
Name: dask-azureblobfs
Version: 0.1.0
Summary: Azure Blob Storage Backend for Dask
Home-page: https://github.com/manish/dask-azureblobfs
Author: Manish Sinha
Author-email: masinha@microsoft.com
License: MIT
Keywords: azureblobfs
Platform: UNKNOWN
Classifier: Development Status :: 2 - Pre-Alpha
Classifier: Intended Audience :: Developers
Classifier: Natural Language :: English
Classifier: Programming Language :: Python :: 2.7
Classifier: Programming Language :: Python :: 3.6
Classifier: Programming Language :: Python :: 3.7
Classifier: License :: OSI Approved :: MIT License
Requires-Dist: dask
Requires-Dist: azure-storage-blob
